datasette_google_analytics/__init__.py
datasette_google_analytics/templates/base.html
datasette_google_analytics-0.1.2.dist-info/licenses/LICENSE
datasette_google_analytics-0.1.2.dist-info/METADATA
datasette_google_analytics-0.1.2.dist-info/WHEEL
datasette_google_analytics-0.1.2.dist-info/entry_points.txt
datasette_google_analytics-0.1.2.dist-info/top_level.txt
datasette_google_analytics-0.1.2.dist-info/RECORD
