Metadata-Version: 2.4
Name: datasette-google-analytics
Version: 0.1.2
Summary: Datasette plugin that adds Google Analytics tracking code to your Datasette instance
Home-page: https://github.com/ngshiheng/datasette-google-analytics
Author: Jerry Ng
License: MIT
Project-URL: Issues, https://github.com/ngshiheng/datasette-google-analytics/issues
Project-URL: CI, https://github.com/ngshiheng/datasette-google-analytics/actions
Project-URL: Changelog, https://github.com/ngshiheng/datasette-google-analytics/releases
Classifier: Framework :: Datasette
Requires-Python: >=3.9
License-File: LICENSE
Requires-Dist: datasette>=0.54
Provides-Extra: test
Requires-Dist: beautifulsoup4; extra == "test"
Requires-Dist: pytest-asyncio; extra == "test"
Requires-Dist: pytest; extra == "test"
Requires-Dist: python-semantic-release; extra == "test"
Dynamic: author
Dynamic: classifier
Dynamic: description
Dynamic: description-content-type
Dynamic: home-page
Dynamic: license
Dynamic: license-file
Dynamic: project-url
Dynamic: provides-extra
Dynamic: requires-dist
Dynamic: requires-python
Dynamic: summary
